odoo/addons/mgmtsystem_audit/README.rst
odoo/addons/mgmtsystem_audit/__init__.py
odoo/addons/mgmtsystem_audit/__manifest__.py
odoo/addons/mgmtsystem_audit/data/base_automation.xml
odoo/addons/mgmtsystem_audit/data/ir_actions_server.xml
odoo/addons/mgmtsystem_audit/data/ir_sequence.xml
odoo/addons/mgmtsystem_audit/data/mail_template.xml
odoo/addons/mgmtsystem_audit/demo/demo_audit.xml
odoo/addons/mgmtsystem_audit/i18n/am.po
odoo/addons/mgmtsystem_audit/i18n/ca.po
odoo/addons/mgmtsystem_audit/i18n/de.po
odoo/addons/mgmtsystem_audit/i18n/el_GR.po
odoo/addons/mgmtsystem_audit/i18n/es.po
odoo/addons/mgmtsystem_audit/i18n/es_CO.po
odoo/addons/mgmtsystem_audit/i18n/es_ES.po
odoo/addons/mgmtsystem_audit/i18n/fi.po
odoo/addons/mgmtsystem_audit/i18n/fr.po
odoo/addons/mgmtsystem_audit/i18n/gl.po
odoo/addons/mgmtsystem_audit/i18n/hr_HR.po
odoo/addons/mgmtsystem_audit/i18n/hu.po
odoo/addons/mgmtsystem_audit/i18n/it.po
odoo/addons/mgmtsystem_audit/i18n/lv.po
odoo/addons/mgmtsystem_audit/i18n/mgmtsystem_audit.pot
odoo/addons/mgmtsystem_audit/i18n/nb.po
odoo/addons/mgmtsystem_audit/i18n/nl.po
odoo/addons/mgmtsystem_audit/i18n/nl_NL.po
odoo/addons/mgmtsystem_audit/i18n/nn.po
odoo/addons/mgmtsystem_audit/i18n/pt.po
odoo/addons/mgmtsystem_audit/i18n/pt_BR.po
odoo/addons/mgmtsystem_audit/i18n/pt_PT.po
odoo/addons/mgmtsystem_audit/i18n/sl.po
odoo/addons/mgmtsystem_audit/i18n/sv.po
odoo/addons/mgmtsystem_audit/i18n/tr.po
odoo/addons/mgmtsystem_audit/i18n/vi.po
odoo/addons/mgmtsystem_audit/models/__init__.py
odoo/addons/mgmtsystem_audit/models/mgmtsystem_audit.py
odoo/addons/mgmtsystem_audit/models/mgmtsystem_nonconformity.py
odoo/addons/mgmtsystem_audit/models/mgmtsystem_verification_line.py
odoo/addons/mgmtsystem_audit/report/audit.xml
odoo/addons/mgmtsystem_audit/report/mgmtsystem_audit_pivot.xml
odoo/addons/mgmtsystem_audit/report/report.xml
odoo/addons/mgmtsystem_audit/report/verification.xml
odoo/addons/mgmtsystem_audit/security/ir.model.access.csv
odoo11_addon_mgmtsystem_audit-11.0.1.0.0.99.dev8.dist-info/METADATA
odoo11_addon_mgmtsystem_audit-11.0.1.0.0.99.dev8.dist-info/WHEEL
odoo11_addon_mgmtsystem_audit-11.0.1.0.0.99.dev8.dist-info/top_level.txt
odoo11_addon_mgmtsystem_audit-11.0.1.0.0.99.dev8.dist-info/RECORD
